malpz/__init__.py
malpz-9.0.13.dist-info/METADATA
malpz-9.0.13.dist-info/WHEEL
malpz-9.0.13.dist-info/entry_points.txt
malpz-9.0.13.dist-info/top_level.txt
malpz-9.0.13.dist-info/RECORD
