Metadata-Version: 2.4
Name: malpz
Version: 9.0.13
Summary: The MALPZ (Malware Pickled Zip) format describes a method of neutering malware while providing a simple, extensible mechanism for capturing metadata
Author: Azul
Author-email: azul@asd.gov.au
Keywords: malware,malpz,neuter
Platform: any
Classifier: Development Status :: 5 - Production/Stable
Classifier: License :: OSI Approved :: MIT License
Classifier: Programming Language :: Python
Classifier: Programming Language :: Python :: 3
Classifier: Programming Language :: Python :: 3.9
Classifier: Programming Language :: Python :: 3.10
Classifier: Programming Language :: Python :: 3.11
Classifier: Programming Language :: Python :: 3.12
Classifier: Programming Language :: Python :: 3.13
Classifier: Programming Language :: Python :: 3.14
Classifier: Intended Audience :: Developers
Classifier: Topic :: Software Development :: Libraries
Requires-Python: >=3.9
Dynamic: author
Dynamic: author-email
Dynamic: classifier
Dynamic: description
Dynamic: description-content-type
Dynamic: keywords
Dynamic: platform
Dynamic: requires-python
Dynamic: summary
